cloudbeds_pms_v1_2/__init__.py
cloudbeds_pms_v1_2/api_client.py
cloudbeds_pms_v1_2/api_response.py
cloudbeds_pms_v1_2/configuration.py
cloudbeds_pms_v1_2/exceptions.py
cloudbeds_pms_v1_2/py.typed
cloudbeds_pms_v1_2/rest.py
cloudbeds_pms_v1_2/api/__init__.py
cloudbeds_pms_v1_2/api/adjustment_api.py
cloudbeds_pms_v1_2/api/allotment_blocks_api.py
cloudbeds_pms_v1_2/api/app_settings_api.py
cloudbeds_pms_v1_2/api/authentication_api.py
cloudbeds_pms_v1_2/api/currency_api.py
cloudbeds_pms_v1_2/api/custom_fields_api.py
cloudbeds_pms_v1_2/api/dashboard_api.py
cloudbeds_pms_v1_2/api/emails_api.py
cloudbeds_pms_v1_2/api/groups_api.py
cloudbeds_pms_v1_2/api/guest_api.py
cloudbeds_pms_v1_2/api/hotel_api.py
cloudbeds_pms_v1_2/api/house_account_api.py
cloudbeds_pms_v1_2/api/housekeeping_api.py
cloudbeds_pms_v1_2/api/integration_api.py
cloudbeds_pms_v1_2/api/invoices_api.py
cloudbeds_pms_v1_2/api/item_api.py
cloudbeds_pms_v1_2/api/package_api.py
cloudbeds_pms_v1_2/api/payment_api.py
cloudbeds_pms_v1_2/api/rate_api.py
cloudbeds_pms_v1_2/api/reservation_api.py
cloudbeds_pms_v1_2/api/room_api.py
cloudbeds_pms_v1_2/api/taxes_and_fees_api.py
cloudbeds_pms_v1_2/api/user_api.py
cloudbeds_pms_v1_2/models/__init__.py
cloudbeds_pms_v1_2/models/delete_adjustment_response.py
cloudbeds_pms_v1_2/models/delete_guest_note_response.py
cloudbeds_pms_v1_2/models/delete_reservation_note_response.py
cloudbeds_pms_v1_2/models/delete_room_block_response.py
cloudbeds_pms_v1_2/models/delete_webhook_response.py
cloudbeds_pms_v1_2/models/get_allotment_blocks_response.py
cloudbeds_pms_v1_2/models/get_allotment_blocks_response_data_inner.py
cloudbeds_pms_v1_2/models/get_allotment_blocks_response_data_inner_allotment_intervals_inner.py
cloudbeds_pms_v1_2/models/get_allotment_blocks_response_data_inner_allotment_intervals_inner_availability_inner.py
cloudbeds_pms_v1_2/models/get_allotment_blocks_response_data_inner_allotment_intervals_inner_restrictions.py
cloudbeds_pms_v1_2-1.3.0.dist-info/licenses/LICENSE
cloudbeds_pms_v1_2-1.3.0.dist-info/METADATA
cloudbeds_pms_v1_2-1.3.0.dist-info/WHEEL
cloudbeds_pms_v1_2-1.3.0.dist-info/top_level.txt
cloudbeds_pms_v1_2-1.3.0.dist-info/RECORD
